README.md
setup.cfg
setup.py
marblecutter/__init__.py
marblecutter/mosaic.py
marblecutter/stats.py
marblecutter/tiling.py
marblecutter/utils.py
marblecutter/web.py
marblecutter.egg-info/PKG-INFO
marblecutter.egg-info/SOURCES.txt
marblecutter.egg-info/dependency_links.txt
marblecutter.egg-info/not-zip-safe
marblecutter.egg-info/requires.txt
marblecutter.egg-info/top_level.txt
marblecutter/catalogs/__init__.py
marblecutter/catalogs/postgis.py
marblecutter/formats/__init__.py
marblecutter/formats/color_ramp.py
marblecutter/formats/geotiff.py
marblecutter/formats/png.py
marblecutter/static/images/transparent.png
marblecutter/templates/preview.html
marblecutter/templates/wmts.xml
marblecutter/transformations/__init__.py
marblecutter/transformations/buffer.py
marblecutter/transformations/image.py
marblecutter/transformations/utils.py