Metadata-Version: 1.0
Name: marblecutter
Version: 0.3.1
Summary: Raster manipulation
Home-page: https://github.com/mojodna/marblecutter
Author: Seth Fitzsimmons
Author-email: seth@mojodna.net
License: BSD
Platform: UNKNOWN
